preemo/__init__.py
preemo/gen/__init__.py
preemo/gen/endpoints/__init__.py
preemo/gen/endpoints/batch_allocate_artifact_part_pb2.py
preemo/gen/endpoints/batch_allocate_artifact_part_pb2.pyi
preemo/gen/endpoints/batch_create_artifact_pb2.py
preemo/gen/endpoints/batch_create_artifact_pb2.pyi
preemo/gen/endpoints/batch_execute_function_pb2.py
preemo/gen/endpoints/batch_execute_function_pb2.pyi
preemo/gen/endpoints/batch_finalize_artifact_pb2.py
preemo/gen/endpoints/batch_finalize_artifact_pb2.pyi
preemo/gen/endpoints/batch_get_artifact_download_url_pb2.py
preemo/gen/endpoints/batch_get_artifact_download_url_pb2.pyi
preemo/gen/endpoints/batch_get_artifact_pb2.py
preemo/gen/endpoints/batch_get_artifact_pb2.pyi
preemo/gen/endpoints/batch_get_artifact_upload_url_pb2.py
preemo/gen/endpoints/batch_get_artifact_upload_url_pb2.pyi
preemo/gen/endpoints/check_function_pb2.py
preemo/gen/endpoints/check_function_pb2.pyi
preemo/gen/endpoints/execute_function_pb2.py
preemo/gen/endpoints/execute_function_pb2.pyi
preemo/gen/endpoints/header_pb2.py
preemo/gen/endpoints/header_pb2.pyi
preemo/gen/endpoints/register_function_pb2.py
preemo/gen/endpoints/register_function_pb2.pyi
preemo/gen/endpoints/sdk_server_ready_pb2.py
preemo/gen/endpoints/sdk_server_ready_pb2.pyi
preemo/gen/endpoints/terminate_pb2.py
preemo/gen/endpoints/terminate_pb2.pyi
preemo/gen/models/__init__.py
preemo/gen/models/artifact_type_pb2.py
preemo/gen/models/artifact_type_pb2.pyi
preemo/gen/models/registered_function_pb2.py
preemo/gen/models/registered_function_pb2.pyi
preemo/gen/models/value_pb2.py
preemo/gen/models/value_pb2.pyi
preemo/gen/services/__init__.py
preemo/gen/services/sdk_pb2_grpc.py
preemo/gen/services/sdk_pb2_grpc.pyi
preemo/gen/services/worker_pb2_grpc.py
preemo/gen/services/worker_pb2_grpc.pyi
preemo/py.typed
preemo/worker/__init__.py
preemo/worker/__init__.pyi
preemo/worker/_artifact_manager.py
preemo/worker/_bytes.py
preemo/worker/_env_manager.py
preemo/worker/_function_registry.py
preemo_worker_sdk-0.6.0.dist-info/LICENSE
preemo_worker_sdk-0.6.0.dist-info/METADATA
preemo_worker_sdk-0.6.0.dist-info/WHEEL
preemo_worker_sdk-0.6.0.dist-info/RECORD
