Metadata-Version: 2.1
Name: preemo-worker-sdk
Version: 0.6.0
Summary: 
Home-page: https://www.preemo.io/
License: MIT
Author: Forrest Moret
Author-email: forrest@preemo.io
Requires-Python: >=3.8.13,<4.0.0
Classifier: License :: OSI Approved :: MIT License
Classifier: Operating System :: OS Independent
Classifier: Programming Language :: Python :: 3
Classifier: Programming Language :: Python :: 3.9
Classifier: Programming Language :: Python :: 3.10
Classifier: Programming Language :: Python :: 3.11
Requires-Dist: grpcio (>=1.51.3,<2.0.0)
Requires-Dist: protobuf (>=4.21.12,<5.0.0)
Requires-Dist: pydantic (>=1.10.6,<2.0.0)
Requires-Dist: requests (>=2.28.2,<3.0.0)
Project-URL: Repository, https://github.com/Preemo-Inc/worker-sdk
